CHANGELOG
LICENSE
MANIFEST.in
README.md
_README.md
__init__.py
setup.cfg
setup.py
test.py
test2.py
Webmaster.egg-info/PKG-INFO
Webmaster.egg-info/SOURCES.txt
Webmaster.egg-info/dependency_links.txt
Webmaster.egg-info/entry_points.txt
Webmaster.egg-info/not-zip-safe
Webmaster.egg-info/requires.txt
Webmaster.egg-info/top_level.txt
devtest6/__init__.py
devtest6/app_www.py
devtest6/manage.py
devtest6/application/__init__.py
devtest6/application/config.py
devtest6/application/exceptions.py
devtest6/application/model.py
devtest6/application/extras/__init__.py
devtest6/application/www/__init__.py
devtest6/application/www/views.py
tests/__init__.py
tests/config.py
tests/test_core.py
tests/test_decorators.py
tests/test_ext.py
tests/test_utils.py
webmaster/__about__.py
webmaster/__about__.pyc
webmaster/__init__.py
webmaster/__init__.pyc
webmaster/cli.py
webmaster/cli.pyc
webmaster/core.py
webmaster/core.pyc
webmaster/decorators.py
webmaster/decorators.pyc
webmaster/exceptions.py
webmaster/exceptions.pyc
webmaster/ext.py
webmaster/ext.pyc
webmaster/htmlcompress_ext.py
webmaster/htmlcompress_ext.pyc
webmaster/markdown_ext.py
webmaster/markdown_ext.pyc
webmaster/utils.py
webmaster/utils.pyc
webmaster/app-skel/app.py
webmaster/app-skel/blank
webmaster/app-skel/config.py
webmaster/app-skel/manage.py
webmaster/app-skel/model.py
webmaster/app-skel/propel.yml
webmaster/app-skel/app/__init__.py
webmaster/app-skel/app/views.py
webmaster/app-skel/app/static/assets.yml
webmaster/app-skel/app/static/css/admin.css
webmaster/app-skel/app/static/css/style.css
webmaster/app-skel/app/static/images/blank
webmaster/app-skel/app/static/js/admin.js
webmaster/app-skel/app/static/js/app.js
webmaster/app-skel/app/templates/layout.html
webmaster/app-skel/app/templates/macros.html
webmaster/app-skel/app/templates/Account/index.html
webmaster/app-skel/app/templates/Account/no_login.html
webmaster/app-skel/app/templates/Account/upload.html
webmaster/app-skel/app/templates/Admin/index.html
webmaster/app-skel/app/templates/Index/index.html
webmaster/app-skel/app/templates/Index/index2.html
webmaster/app-skel/data/mailer-templates/contact-us.txt
webmaster/app-skel/data/mailer-templates/default-template.txt
